<?xml version="1.0" encoding="UTF-8"?>
<configuration>

  <springProperty scope="context" name="APP_NAME" source="spring.application.name" defaultValue="app"/>
  <springProperty scope="context" name="SPRING_PROFILES_ACTIVE" source="spring.profiles.active" defaultValue="local"/>

  <appender name="FILE_APP" class="ch.qos.logback.core.rolling.RollingFileAppender">
    <file>/logs/app/application.log</file>
    <rollingPolicy class="ch.qos.logback.core.rolling.SizeAndTimeBasedRollingPolicy">
      <fileNamePattern>/logs/app/application.%d{yyyy-MM-dd}.%i.log.gz</fileNamePattern>
      <maxFileSize>50MB</maxFileSize>
      <maxHistory>30</maxHistory>
      <totalSizeCap>2GB</totalSizeCap>
      <cleanHistoryOnStart>true</cleanHistoryOnStart>
    </rollingPolicy>
    <encoder class="net.logstash.logback.encoder.LogstashEncoder">
      <customFields>{"app":"${APP_NAME}","env":"${SPRING_PROFILES_ACTIVE}"}</customFields>
    </encoder>
  </appender>

  <appender name="FILE_ERROR" class="ch.qos.logback.core.rolling.RollingFileAppender">
    <file>/logs/app/error.log</file>
    <filter class="ch.qos.logback.classic.filter.ThresholdFilter">
      <level>ERROR</level>
    </filter>
    <rollingPolicy class="ch.qos.logback.core.rolling.TimeBasedRollingPolicy">
      <fileNamePattern>/logs/app/error.%d{yyyy-MM-dd}.log.gz</fileNamePattern>
      <maxHistory>90</maxHistory>
      <totalSizeCap>500MB</totalSizeCap>
    </rollingPolicy>
    <encoder class="net.logstash.logback.encoder.LogstashEncoder">
      <customFields>{"app":"${APP_NAME}","level_file":"error"}</customFields>
    </encoder>
  </appender>

  <appender name="FILE_AUDIT" class="ch.qos.logback.core.rolling.RollingFileAppender">
    <file>/logs/app/audit.log</file>
    <rollingPolicy class="ch.qos.logback.core.rolling.TimeBasedRollingPolicy">
      <fileNamePattern>/logs/app/audit.%d{yyyy-MM-dd}.log.gz</fileNamePattern>
      <maxHistory>365</maxHistory>
      <totalSizeCap>1GB</totalSizeCap>
    </rollingPolicy>
    <encoder class="net.logstash.logback.encoder.LogstashEncoder"/>
  </appender>

  <logger name="AUDIT" level="INFO" additivity="false">
    <appender-ref ref="FILE_AUDIT"/>
  </logger>

  <logger name="org.hibernate.SQL" level="WARN"/>
  <logger name="org.springframework.web" level="WARN"/>
  <logger name="com.zaxxer.hikari" level="WARN"/>

  <springProfile name="local,dev">
    <appender name="CONSOLE" class="ch.qos.logback.core.ConsoleAppender">
      <encoder class="net.logstash.logback.encoder.LogstashEncoder"/>
    </appender>

    <root level="INFO">
      <appender-ref ref="FILE_APP"/>
      <appender-ref ref="FILE_ERROR"/>
      <appender-ref ref="CONSOLE"/>
    </root>
  </springProfile>

  <springProfile name="!local &amp; !dev">
    <root level="INFO">
      <appender-ref ref="FILE_APP"/>
      <appender-ref ref="FILE_ERROR"/>
    </root>
  </springProfile>

</configuration>
